tinygwas.cpython-39-darwin.so
tinygwas-0.2.dist-info/METADATA
tinygwas-0.2.dist-info/WHEEL
tinygwas-0.2.dist-info/top_level.txt
tinygwas-0.2.dist-info/RECORD
